qingstor_sdk-2.6.0-py3.5-nspkg.pth
qingstor/sdk/__init__.py
qingstor/sdk/build.py
qingstor/sdk/config.py
qingstor/sdk/constant.py
qingstor/sdk/error.py
qingstor/sdk/request.py
qingstor/sdk/unpack.py
qingstor/sdk/client/__init__.py
qingstor/sdk/client/upload_client.py
qingstor/sdk/service/__init__.py
qingstor/sdk/service/bucket.py
qingstor/sdk/service/qingstor.py
qingstor/sdk/utils/__init__.py
qingstor/sdk/utils/file_chunk.py
qingstor/sdk/utils/helper.py
qingstor_sdk-2.6.0.dist-info/DESCRIPTION.rst
qingstor_sdk-2.6.0.dist-info/METADATA
qingstor_sdk-2.6.0.dist-info/RECORD
qingstor_sdk-2.6.0.dist-info/WHEEL
qingstor_sdk-2.6.0.dist-info/metadata.json
qingstor_sdk-2.6.0.dist-info/namespace_packages.txt
qingstor_sdk-2.6.0.dist-info/top_level.txt
