Metadata-Version: 2.0
Name: qingstor-sdk
Version: 2.6.0
Summary: The official QingStor SDK for the Python programming language.
Home-page: https://github.com/yunify/qingstor-sdk-python
Author: Yunify SDK Group
Author-email: sdk_group@yunify.com
License: Apache License 2.0
Platform: UNKNOWN
Classifier: Development Status :: 5 - Production/Stable
Classifier: Intended Audience :: Developers
Classifier: Natural Language :: English
Classifier: License :: OSI Approved :: Apache Software License
Classifier: Programming Language :: Python
Classifier: Programming Language :: Python :: 3
Classifier: Programming Language :: Python :: 3.6
Classifier: Programming Language :: Python :: 3.7
Classifier: Programming Language :: Python :: 3.8
Classifier: Programming Language :: Python :: 3.9
Requires-Dist: PyYAML
Requires-Dist: requests
